metpyrad/__init__.py
metpyrad/hidex300.py
metpyrad-0.0.1.dist-info/METADATA
metpyrad-0.0.1.dist-info/WHEEL
metpyrad-0.0.1.dist-info/licenses/LICENSE
metpyrad-0.0.1.dist-info/RECORD
