Metadata-Version: 2.4
Name: metpyrad
Version: 0.0.1
Summary: Tools for radionuclide metrology
Project-URL: Repository, https://github.com/lmri-met/metpyrad
Project-URL: Documentation, https://github.com/lmri-met/metpyrad#readme
Project-URL: Issues, https://github.com/lmri-met/metpyrad/issues
Author-email: Xandra Campo <xandra.campo@ciemat.es>
Maintainer-email: Xandra Campo <xandra.campo@ciemat.es>
License:                     GNU GENERAL PUBLIC LICENSE
License-File: LICENSE
Keywords: TDCR,metrology,radionuclide
Classifier: Development Status :: 3 - Alpha
Classifier: Intended Audience :: Science/Research
Classifier: License :: OSI Approved :: GNU General Public License v3 (GPLv3)
Classifier: Programming Language :: Python
Classifier: Topic :: Scientific/Engineering :: Physics
Requires-Python: >=3.8
Requires-Dist: matplotlib
Requires-Dist: numpy
Requires-Dist: pandas
Provides-Extra: dev
Requires-Dist: hatch; extra == 'dev'
Requires-Dist: pydata-sphinx-theme; extra == 'dev'
Requires-Dist: pytest; extra == 'dev'
Requires-Dist: pytest-cov; extra == 'dev'
Requires-Dist: sphinx; extra == 'dev'
Requires-Dist: sphinx-design; extra == 'dev'
